goenrichment/__init__.py
goenrichment/enrichment.py
goenrichment/go.py
goenrichment/goenrich.py
goenrichment/goenrichDB.py
goenrichment/graph.py
goenrichment/parsers.py
goenrichment-1.0.3.data/data/README.rst
tests/__init__.py
tests/test_godb.py
goenrichment-1.0.3.dist-info/LICENSE
goenrichment-1.0.3.dist-info/METADATA
goenrichment-1.0.3.dist-info/WHEEL
goenrichment-1.0.3.dist-info/entry_points.txt
goenrichment-1.0.3.dist-info/top_level.txt
goenrichment-1.0.3.dist-info/RECORD
