Metadata-Version: 2.1
Name: goenrichment
Version: 1.0.3
Summary: GO enrichment analysis from a list of gene names using a precomputed database
Home-page: https://gitlab.com/r78v10a07/goenrichment
Author: Vera Alvarez, Roberto
Author-email: veraalva@ncbi.nlm.nih.gov
Maintainer: Vera Alvarez, Roberto
Maintainer-email: veraalva@ncbi.nlm.nih.gov
License: Public Domain
Project-URL: Documentation, https://gitlab.com/r78v10a07/goenrichment/issues
Project-URL: Source, https://gitlab.com/r78v10a07/goenrichment
Project-URL: Tracker, https://gitlab.com/r78v10a07/goenrichment/issues
Keywords: Jupyter NGS
Platform: UNKNOWN
Classifier: Development Status :: 3 - Alpha
Classifier: Framework :: Jupyter
Classifier: Intended Audience :: Science/Research
Classifier: License :: Public Domain
Classifier: Natural Language :: English
Classifier: Operating System :: Unix
Classifier: Programming Language :: Python :: 3
Classifier: Programming Language :: Python :: 3.7
Classifier: Programming Language :: Python :: 3.8
Classifier: Topic :: Scientific/Engineering :: Bio-Informatics
License-File: LICENSE
Requires-Dist: numpy
Requires-Dist: scipy
Requires-Dist: statsmodels
Requires-Dist: pandas
Requires-Dist: networkx
